[{
            "_id": "6828064fdb9bd4671fd1127b",
            "title": "insmouth fish",
            "price": 2,
            "stock": 500,
            "description": "'Ough, What do smell like?' Just like the best Massachusetts fresh fish, fish from Insmouth, 2 dollars per unity",
            "category": "insmouth fish",
            "active": true,
            "image_url": "https://images.unsplash.com/photo-1682686581551-867e0b208bd1?q=80&w=1740&auto=format&fit=crop&ixlib=rb-4.0.3&ixid=M3wxMjA3fDF8MHxwaG90by1wYWdlfHx8fGVufDB8fHx8fA%3D%3D",
            "seller_name": "2",
            "__v": 0,
            "createdAt": "2025-05-17T03:45:19.970Z",
            "updatedAt": "2025-05-17T03:45:19.970Z"
        }, {
            "_id": "6828064fdb9bd4671fd1127c",
            "title": "image 3",
            "price": 1000,
            "stock": 30,
            "description": "A cyclopean monolith that measures meters, perfect for decorating a garden and bringing strange events into your miserable life.",
            "category": "Submarine Obelisk",
            "active": true,
            "image_url": "https://images.unsplash.com/photo-1682695797221-8164ff1fafc9?q=80&w=1740&auto=format&fit=crop&ixlib=rb-4.0.3&ixid=M3wxMjA3fDF8MHxwaG90by1wYWdlfHx8fGVufDB8fHx8fA%3D%3D",
            "seller_name": "3",
            "__v": 0,
            "createdAt": "2025-05-17T03:45:19.970Z",
            "updatedAt": "2025-05-17T03:45:19.970Z"
        }, {
            "_id": "6828064fdb9bd4671fd11281",
            "title": "image 8",
            "price": 100,
            "stock": 25,
            "description": "Spores, and spores, and spores...",
            "category": "Magic",
            "active": true,
            "image_url": "https://plus.unsplash.com/premium_photo-1698442704192-086265cf630e?q=80&w=1738&auto=format&fit=crop&ixlib=rb-4.0.3&ixid=M3wxMjA3fDB8MHxwaG90by1wYWdlfHx8fGVufDB8fHx8fA%3D%3D",
            "seller_name": "8",
            "__v": 0,
            "createdAt": "2025-05-17T03:45:19.971Z",
            "updatedAt": "2025-05-17T03:45:19.971Z"
        }, {
            "_id": "6828064fdb9bd4671fd1127e",
            "title": "image 5",
            "price": 50,
            "stock": 40,
            "description": "Spores, and spores, and spores...",
            "category": "Magic",
            "active": true,
            "image_url": "https://images.unsplash.com/photo-1700839154423-83ea2246621b?q=80&w=1740&auto=format&fit=crop&ixlib=rb-4.0.3&ixid=M3wxMjA3fDB8MHxwaG90by1wYWdlfHx8fGVufDB8fHx8fA%3D%3D",
            "seller_name": "Charles Dexter Ward",
            "__v": 0,
            "createdAt": "2025-05-17T03:45:19.971Z",
            "updatedAt": "2025-05-17T03:57:52.451Z",
            "seller_id": "68280940e425903247f36b15"
        }, {
            "_id": "6828064fdb9bd4671fd1127f",
            "title": "image 6",
            "price": 40,
            "stock": 70,
            "description": "Spores, and spores, and spores...",
            "category": "Magic",
            "active": true,
            "image_url": "https://images.unsplash.com/photo-1700770845346-7e95de335eb0?q=80&w=1632&auto=format&fit=crop&ixlib=rb-4.0.3&ixid=M3wxMjA3fDB8MHxwaG90by1wYWdlfHx8fGVufDB8fHx8fA%3D%3D",
            "seller_name": "Charles Dexter Ward",
            "__v": 0,
            "createdAt": "2025-05-17T03:45:19.971Z",
            "updatedAt": "2025-05-17T03:57:52.452Z",
            "seller_id": "68280940e425903247f36b15"
        }, {
            "_id": "6828064fdb9bd4671fd11280",
            "title": "image 7",
            "price": 70,
            "stock": 25,
            "description": "Spores, and spores, and spores...",
            "category": "Magic",
            "active": true,
            "image_url": "https://images.unsplash.com/photo-1700751639138-e6628c42b558?q=80&w=1740&auto=format&fit=crop&ixlib=rb-4.0.3&ixid=M3wxMjA3fDB8MHxwaG90by1wYWdlfHx8fGVufDB8fHx8fA%3D%3D",
            "seller_name": "7",
            "__v": 0,
            "createdAt": "2025-05-17T03:45:19.971Z",
            "updatedAt": "2025-05-17T03:45:19.971Z"
        }, {
            "_id": "6828064fdb9bd4671fd11282",
            "title": "image 9",
            "price": 10,
            "stock": 75,
            "description": "Spores, and spores, and spores...",
            "category": "Magic",
            "active": true,
            "image_url": "https://images.unsplash.com/photo-1700753227268-8832c285591e?q=80&w=1744&auto=format&fit=crop&ixlib=rb-4.0.3&ixid=M3wxMjA3fDB8MHxwaG90by1wYWdlfHx8fGVufDB8fHx8fA%3D%3D",
            "seller_name": "9",
            "__v": 0,
            "createdAt": "2025-05-17T03:45:19.971Z",
            "updatedAt": "2025-05-17T03:45:19.971Z"
        }, {
            "_id": "6828064fdb9bd4671fd11283",
            "title": "image 10",
            "price": 10,
            "stock": 90,
            "description": "Spores, and spores, and spores...",
            "category": "Magic",
            "active": true,
            "image_url": "https://images.unsplash.com/photo-1700769025506-6c3dcb9ec9b7?q=80&w=1664&auto=format&fit=crop&ixlib=rb-4.0.3&ixid=M3wxMjA3fDB8MHxwaG90by1wYWdlfHx8fGVufDB8fHx8fA%3D%3D",
            "seller_name": "10",
            "__v": 0,
            "createdAt": "2025-05-17T03:45:19.971Z",
            "updatedAt": "2025-05-17T03:45:19.971Z"
        }, {
            "_id": "6828064fdb9bd4671fd1127a",
            "title": "godfish idol",
            "price": 100,
            "stock": 5,
            "description": "rather for worshiping or simply decoration, everyone will need one as the sea rises to reclaim this doomed world...",
            "category": "stone",
            "active": true,
            "image_url": "https://images.unsplash.com/photo-1682695796954-bad0d0f59ff1?q=80&w=1740&auto=format&fit=crop&ixlib=rb-4.0.3&ixid=M3wxMjA3fDF8MHxwaG90by1wYWdlfHx8fGVufDB8fHx8fA%3D%3D",
            "seller_name": "1",
            "__v": 0,
            "createdAt": "2025-05-17T03:45:19.970Z",
            "updatedAt": "2025-05-17T03:45:19.970Z"
        }, {
            "_id": "6828064fdb9bd4671fd1127d",
            "title": "Necronomicon (Order of Dagon edition)",
            "price": 80,
            "stock": 100,
            "description": "Lost civilizations older than Earth, rites for communing with the blind idiot god Azathoth, and the geometry of forgotten stars under which dread Cthulhu dreams. The Necronomicon is no mere book—it is an invitation to annihilation.",
            "category": "Magic",
            "active": true,
            "image_url": "https://images.unsplash.com/photo-1700744228339-03c725f5ee57?q=80&w=1740&auto=format&fit=crop&ixlib=rb-4.0.3&ixid=M3wxMjA3fDB8MHxwaG90by1wYWdlfHx8fGVufDB8fHx8fA%3D%3D",
            "seller_name": "Abdul Alhazred, the Mad Arab",
            "__v": 0,
            "createdAt": "2025-05-17T03:45:19.971Z",
            "updatedAt": "2025-05-17T03:45:19.971Z"
        },